aioeafm/__init__.py
aioeafm-1.0.0.dist-info/LICENSE
aioeafm-1.0.0.dist-info/WHEEL
aioeafm-1.0.0.dist-info/METADATA
aioeafm-1.0.0.dist-info/RECORD
